how_old.py
how_old-0.0.4.dist-info/METADATA
how_old-0.0.4.dist-info/WHEEL
how_old-0.0.4.dist-info/RECORD
